managebac_api/__init__.py
managebac_api/api.py
managebac_api-1.0.0.dist-info/LICENSE
managebac_api-1.0.0.dist-info/METADATA
managebac_api-1.0.0.dist-info/WHEEL
managebac_api-1.0.0.dist-info/top_level.txt
managebac_api-1.0.0.dist-info/RECORD
